PC/testbenches/PC_Register.sv
module PC_Register #(
	parameter WIDTH_IN = 32,
    parameter WIDTH_OUT = 32
)(
    input logic clk,
    input logic rst,
    input logic [WIDTH_IN-1:0] data_in,
    output logic [WIDTH_OUT-1:0] data_out
);

always_ff @(posedge clk, posedge rst) begin
    if(rst) begin
        data_out <= 0;
    end else begin
        data_out <= data_in;
    end
end
  


endmodule

PC/testbenches/mux.sv
module mux #(
	parameter WIDTH = 32
)(
  // interface signals
  input logic [WIDTH-1:0] inputA,
  input logic [WIDTH-1:0] inputB,
  input logic sel,
  output logic [WIDTH-1:0] data_out
);

always_comb begin
    if (sel) begin
        data_out = inputA;
    end else begin
        data_out = inputB;
    end
end

endmodule

PC/testbenches/adder.sv
module adder #(
	parameter INPUT_WIDTH = 32
)(
    // interface signals
    input logic [INPUT_WIDTH-1:0] a,
    input logic [INPUT_WIDTH-1:0] b,
    output logic [INPUT_WIDTH-1:0] sum
);

    // internal signals
    logic [INPUT_WIDTH-1:0] sum_internal;

    // internal logic
    assign sum_internal = a + b;

    // output logic
    assign sum = sum_internal;

endmodule

PC/testbenches/PC_top.sv
module PC_top #(
	parameter WIDTH = 32
)(
  // interface signals
  input logic clk,
  input logic rst,
  input logic PCsrc,
  input logic[WIDTH-1:0] ImmOp,
  output logic[WIDTH-1:0] PC
);

logic [WIDTH-1:0] branchPC;
logic [WIDTH-1:0] nextPC;

adder PC_adder(
    .a(PC),
    .b(ImmOp),
    .sum(branchPC)
);

mux PC_mux(
    .inputA(branchPC),
    .inputB(PC + WIDTH'(4)),
    .sel(PCsrc),
    .data_out(nextPC)
);

PC_Register PC_reg(
    .clk(clk),
    .rst(rst),
    .data_in(nextPC),
    .data_out(PC)
);
    
endmodule

PC/testbenches/PC_tb.vcd
$version Generated by VerilatedVcd $end
$date Thu Nov 24 10:06:02 2022 $end
$timescale 1ps $end

 $scope module TOP $end
  $var wire 32 & ImmOp [31:0] $end
  $var wire 32 ' PC [31:0] $end
  $var wire  1 % PCsrc $end
  $var wire  1 # clk $end
  $var wire  1 $ rst $end
  $scope module PC_top $end
   $var wire 32 & ImmOp [31:0] $end
   $var wire 32 ' PC [31:0] $end
   $var wire  1 % PCsrc $end
   $var wire 32 + WIDTH [31:0] $end
   $var wire 32 ( branchPC [31:0] $end
   $var wire  1 # clk $end
   $var wire 32 ) nextPC [31:0] $end
   $var wire  1 $ rst $end
   $scope module PC_adder $end
    $var wire 32 + INPUT_WIDTH [31:0] $end
    $var wire 32 ' a [31:0] $end
    $var wire 32 & b [31:0] $end
    $var wire 32 ( sum [31:0] $end
    $var wire 32 ( sum_internal [31:0] $end
   $upscope $end
   $scope module PC_mux $end
    $var wire 32 + WIDTH [31:0] $end
    $var wire 32 ) data_out [31:0] $end
    $var wire 32 ( inputA [31:0] $end
    $var wire 32 * inputB [31:0] $end
    $var wire  1 % sel $end
   $upscope $end
   $scope module PC_reg $end
    $var wire 32 + WIDTH_IN [31:0] $end
    $var wire 32 + WIDTH_OUT [31:0] $end
    $var wire  1 # clk $end
    $var wire 32 ) data_in [31:0] $end
    $var wire 32 ' data_out [31:0] $end
    $var wire  1 $ rst $end
   $upscope $end
  $upscope $end
 $upscope $end
$enddefinitions $end


#0
1#
1$
0%
b00000000000000000000000000000000 &
b00000000000000000000000000000000 '
b00000000000000000000000000000000 (
b00000000000000000000000000000100 )
b00000000000000000000000000000100 *
b00000000000000000000000000100000 +
#1
0#
#2
1#
0$
#3
0#
#4
1#
b00000000000000000000000000000100 '
b00000000000000000000000000000100 (
b00000000000000000000000000001000 )
b00000000000000000000000000001000 *
#5
0#
#6
1#
b00000000000000000000000000001000 '
b00000000000000000000000000001000 (
b00000000000000000000000000001100 )
b00000000000000000000000000001100 *
#7
0#
#8
1#
b00000000000000000000000000001100 '
b00000000000000000000000000001100 (
b00000000000000000000000000010000 )
b00000000000000000000000000010000 *
#9
0#
#10
1#
b00000000000000000000000000010000 '
b00000000000000000000000000010000 (
b00000000000000000000000000010100 )
b00000000000000000000000000010100 *
#11
0#
#12
1#
b00000000000000000000000000010100 '
b00000000000000000000000000010100 (
b00000000000000000000000000011000 )
b00000000000000000000000000011000 *
#13
0#
#14
1#
b00000000000000000000000000011000 '
b00000000000000000000000000011000 (
b00000000000000000000000000011100 )
b00000000000000000000000000011100 *
#15
0#
#16
1#
b00000000000000000000000000011100 '
b00000000000000000000000000011100 (
b00000000000000000000000000100000 )
b00000000000000000000000000100000 *
#17
0#
#18
1#
b00000000000000000000000000100000 '
b00000000000000000000000000100000 (
b00000000000000000000000000100100 )
b00000000000000000000000000100100 *
#19
0#
#20
1#
b00000000000000000000000000100100 '
b00000000000000000000000000100100 (
b00000000000000000000000000101000 )
b00000000000000000000000000101000 *
#21
0#
#22
1#
b00000000000000000000000000101000 '
b00000000000000000000000000101000 (
b00000000000000000000000000101100 )
b00000000000000000000000000101100 *
#23
0#
#24
1#
b00000000000000000000000000101100 '
b00000000000000000000000000101100 (
b00000000000000000000000000110000 )
b00000000000000000000000000110000 *
#25
0#
#26
1#
1$
b00000000000000000000000000110000 '
b00000000000000000000000000110000 (
b00000000000000000000000000110100 )
b00000000000000000000000000110100 *
#27
0#
b00000000000000000000000000000000 '
b00000000000000000000000000000000 (
b00000000000000000000000000000100 )
b00000000000000000000000000000100 *
#28
1#
0$
#29
0#
#30
1#
b00000000000000000000000000000100 '
b00000000000000000000000000000100 (
b00000000000000000000000000001000 )
b00000000000000000000000000001000 *
#31
0#
#32
1#
b00000000000000000000000000001000 '
b00000000000000000000000000001000 (
b00000000000000000000000000001100 )
b00000000000000000000000000001100 *
#33
0#
#34
1#
b00000000000000000000000000001100 '
b00000000000000000000000000001100 (
b00000000000000000000000000010000 )
b00000000000000000000000000010000 *
#35
0#
#36
1#
b00000000000000000000000000010000 '
b00000000000000000000000000010000 (
b00000000000000000000000000010100 )
b00000000000000000000000000010100 *
#37
0#
#38
1#
b00000000000000000000000000010100 '
b00000000000000000000000000010100 (
b00000000000000000000000000011000 )
b00000000000000000000000000011000 *
#39
0#
#40
1#
b00000000000000000000000000011000 '
b00000000000000000000000000011000 (
b00000000000000000000000000011100 )
b00000000000000000000000000011100 *
#41
0#
#42
1#
b00000000000000000000000000011100 '
b00000000000000000000000000011100 (
b00000000000000000000000000100000 )
b00000000000000000000000000100000 *
#43
0#
#44
1#
b00000000000000000000000000100000 '
b00000000000000000000000000100000 (
b00000000000000000000000000100100 )
b00000000000000000000000000100100 *
#45
0#
#46
1#
b00000000000000000000000000100100 '
b00000000000000000000000000100100 (
b00000000000000000000000000101000 )
b00000000000000000000000000101000 *
#47
0#
#48
1#
b00000000000000000000000000101000 '
b00000000000000000000000000101000 (
b00000000000000000000000000101100 )
b00000000000000000000000000101100 *
#49
0#
#50
1#
b00000000000000000000000000101100 '
b00000000000000000000000000101100 (
b00000000000000000000000000110000 )
b00000000000000000000000000110000 *
#51
0#
#52
1#
b00000000000000000000000000110000 '
b00000000000000000000000000110000 (
b00000000000000000000000000110100 )
b00000000000000000000000000110100 *
#53
0#
#54
1#
b00000000000000000000000000110100 '
b00000000000000000000000000110100 (
b00000000000000000000000000111000 )
b00000000000000000000000000111000 *
#55
0#
#56
1#
b00000000000000000000000000111000 '
b00000000000000000000000000111000 (
b00000000000000000000000000111100 )
b00000000000000000000000000111100 *
#57
0#
#58
1#
b00000000000000000000000000111100 '
b00000000000000000000000000111100 (
b00000000000000000000000001000000 )
b00000000000000000000000001000000 *
#59
0#
#60
1#
b00000000000000000000000001000000 '
b00000000000000000000000001000000 (
b00000000000000000000000001000100 )
b00000000000000000000000001000100 *
#61
0#
#62
1#
b00000000000000000000000001000100 '
b00000000000000000000000001000100 (
b00000000000000000000000001001000 )
b00000000000000000000000001001000 *
#63
0#
#64
1#
b00000000000000000000000001001000 '
b00000000000000000000000001001000 (
b00000000000000000000000001001100 )
b00000000000000000000000001001100 *
#65
0#
#66
1#
b00000000000000000000000001001100 '
b00000000000000000000000001001100 (
b00000000000000000000000001010000 )
b00000000000000000000000001010000 *
#67
0#
#68
1#
b00000000000000000000000001010000 '
b00000000000000000000000001010000 (
b00000000000000000000000001010100 )
b00000000000000000000000001010100 *
#69
0#
#70
1#
b00000000000000000000000001010100 '
b00000000000000000000000001010100 (
b00000000000000000000000001011000 )
b00000000000000000000000001011000 *
#71
0#
#72
1#
b00000000000000000000000001011000 '
b00000000000000000000000001011000 (
b00000000000000000000000001011100 )
b00000000000000000000000001011100 *
#73
0#
#74
1#
b00000000000000000000000001011100 '
b00000000000000000000000001011100 (
b00000000000000000000000001100000 )
b00000000000000000000000001100000 *
#75
0#
#76
1#
b00000000000000000000000001100000 '
b00000000000000000000000001100000 (
b00000000000000000000000001100100 )
b00000000000000000000000001100100 *
#77
0#
#78
1#
b00000000000000000000000001100100 '
b00000000000000000000000001100100 (
b00000000000000000000000001101000 )
b00000000000000000000000001101000 *
#79
0#
#80
1#
b00000000000000000000000001101000 '
b00000000000000000000000001101000 (
b00000000000000000000000001101100 )
b00000000000000000000000001101100 *
#81
0#
#82
1#
b00000000000000000000000001101100 '
b00000000000000000000000001101100 (
b00000000000000000000000001110000 )
b00000000000000000000000001110000 *
#83
0#
#84
1#
b00000000000000000000000001110000 '
b00000000000000000000000001110000 (
b00000000000000000000000001110100 )
b00000000000000000000000001110100 *
#85
0#
#86
1#
b00000000000000000000000001110100 '
b00000000000000000000000001110100 (
b00000000000000000000000001111000 )
b00000000000000000000000001111000 *
#87
0#
#88
1#
b00000000000000000000000001111000 '
b00000000000000000000000001111000 (
b00000000000000000000000001111100 )
b00000000000000000000000001111100 *
#89
0#
#90
1#
b00000000000000000000000001111100 '
b00000000000000000000000001111100 (
b00000000000000000000000010000000 )
b00000000000000000000000010000000 *
#91
0#
#92
1#
b00000000000000000000000010000000 '
b00000000000000000000000010000000 (
b00000000000000000000000010000100 )
b00000000000000000000000010000100 *
#93
0#
#94
1#
b00000000000000000000000010000100 '
b00000000000000000000000010000100 (
b00000000000000000000000010001000 )
b00000000000000000000000010001000 *
#95
0#
#96
1#
b00000000000000000000000010001000 '
b00000000000000000000000010001000 (
b00000000000000000000000010001100 )
b00000000000000000000000010001100 *
#97
0#
#98
1#
b00000000000000000000000010001100 '
b00000000000000000000000010001100 (
b00000000000000000000000010010000 )
b00000000000000000000000010010000 *
#99
0#
#100
1#
b00000000000000000000000010010000 '
b00000000000000000000000010010000 (
b00000000000000000000000010010100 )
b00000000000000000000000010010100 *
#101
0#
#102
1#
b00000000000000000000000010010100 '
b00000000000000000000000010010100 (
b00000000000000000000000010011000 )
b00000000000000000000000010011000 *
#103
0#
#104
1#
b00000000000000000000000010011000 '
b00000000000000000000000010011000 (
b00000000000000000000000010011100 )
b00000000000000000000000010011100 *
#105
0#
#106
1#
b00000000000000000000000010011100 '
b00000000000000000000000010011100 (
b00000000000000000000000010100000 )
b00000000000000000000000010100000 *
#107
0#
#108
1#
b00000000000000000000000010100000 '
b00000000000000000000000010100000 (
b00000000000000000000000010100100 )
b00000000000000000000000010100100 *
#109
0#
#110
1#
b00000000000000000000000010100100 '
b00000000000000000000000010100100 (
b00000000000000000000000010101000 )
b00000000000000000000000010101000 *
#111
0#
#112
1#
b00000000000000000000000010101000 '
b00000000000000000000000010101000 (
b00000000000000000000000010101100 )
b00000000000000000000000010101100 *
#113
0#
#114
1#
b00000000000000000000000010101100 '
b00000000000000000000000010101100 (
b00000000000000000000000010110000 )
b00000000000000000000000010110000 *
#115
0#
#116
1#
b00000000000000000000000010110000 '
b00000000000000000000000010110000 (
b00000000000000000000000010110100 )
b00000000000000000000000010110100 *
#117
0#
#118
1#
b00000000000000000000000010110100 '
b00000000000000000000000010110100 (
b00000000000000000000000010111000 )
b00000000000000000000000010111000 *
#119
0#
#120
1#
b00000000000000000000000010111000 '
b00000000000000000000000010111000 (
b00000000000000000000000010111100 )
b00000000000000000000000010111100 *
#121
0#
#122
1#
b00000000000000000000000010111100 '
b00000000000000000000000010111100 (
b00000000000000000000000011000000 )
b00000000000000000000000011000000 *
#123
0#
#124
1#
b00000000000000000000000011000000 '
b00000000000000000000000011000000 (
b00000000000000000000000011000100 )
b00000000000000000000000011000100 *
#125
0#
#126
1#
b00000000000000000000000011000100 '
b00000000000000000000000011000100 (
b00000000000000000000000011001000 )
b00000000000000000000000011001000 *
#127
0#
#128
1#
b00000000000000000000000011001000 '
b00000000000000000000000011001000 (
b00000000000000000000000011001100 )
b00000000000000000000000011001100 *
#129
0#
#130
1#
b00000000000000000000000011001100 '
b00000000000000000000000011001100 (
b00000000000000000000000011010000 )
b00000000000000000000000011010000 *
#131
0#
#132
1#
b00000000000000000000000011010000 '
b00000000000000000000000011010000 (
b00000000000000000000000011010100 )
b00000000000000000000000011010100 *
#133
0#
#134
1#
b00000000000000000000000011010100 '
b00000000000000000000000011010100 (
b00000000000000000000000011011000 )
b00000000000000000000000011011000 *
#135
0#
#136
1#
b00000000000000000000000011011000 '
b00000000000000000000000011011000 (
b00000000000000000000000011011100 )
b00000000000000000000000011011100 *
#137
0#
#138
1#
b00000000000000000000000011011100 '
b00000000000000000000000011011100 (
b00000000000000000000000011100000 )
b00000000000000000000000011100000 *
#139
0#
#140
1#
b00000000000000000000000011100000 '
b00000000000000000000000011100000 (
b00000000000000000000000011100100 )
b00000000000000000000000011100100 *
#141
0#
#142
1#
b00000000000000000000000011100100 '
b00000000000000000000000011100100 (
b00000000000000000000000011101000 )
b00000000000000000000000011101000 *
#143
0#
#144
1#
b00000000000000000000000011101000 '
b00000000000000000000000011101000 (
b00000000000000000000000011101100 )
b00000000000000000000000011101100 *
#145
0#
#146
1#
b00000000000000000000000011101100 '
b00000000000000000000000011101100 (
b00000000000000000000000011110000 )
b00000000000000000000000011110000 *
#147
0#
#148
1#
b00000000000000000000000011110000 '
b00000000000000000000000011110000 (
b00000000000000000000000011110100 )
b00000000000000000000000011110100 *
#149
0#
#150
1#
b00000000000000000000000011110100 '
b00000000000000000000000011110100 (
b00000000000000000000000011111000 )
b00000000000000000000000011111000 *
#151
0#
#152
1#
b00000000000000000000000011111000 '
b00000000000000000000000011111000 (
b00000000000000000000000011111100 )
b00000000000000000000000011111100 *
#153
0#
#154
1#
b00000000000000000000000011111100 '
b00000000000000000000000011111100 (
b00000000000000000000000100000000 )
b00000000000000000000000100000000 *
#155
0#
#156
1#
b00000000000000000000000100000000 '
b00000000000000000000000100000000 (
b00000000000000000000000100000100 )
b00000000000000000000000100000100 *
#157
0#
#158
1#
b00000000000000000000000100000100 '
b00000000000000000000000100000100 (
b00000000000000000000000100001000 )
b00000000000000000000000100001000 *
#159
0#
#160
1#
b00000000000000000000000100001000 '
b00000000000000000000000100001000 (
b00000000000000000000000100001100 )
b00000000000000000000000100001100 *
#161
0#
#162
1#
b00000000000000000000000100001100 '
b00000000000000000000000100001100 (
b00000000000000000000000100010000 )
b00000000000000000000000100010000 *
#163
0#
#164
1#
b00000000000000000000000100010000 '
b00000000000000000000000100010000 (
b00000000000000000000000100010100 )
b00000000000000000000000100010100 *
#165
0#
#166
1#
b00000000000000000000000100010100 '
b00000000000000000000000100010100 (
b00000000000000000000000100011000 )
b00000000000000000000000100011000 *
#167
0#
#168
1#
b00000000000000000000000100011000 '
b00000000000000000000000100011000 (
b00000000000000000000000100011100 )
b00000000000000000000000100011100 *
#169
0#
#170
1#
b00000000000000000000000100011100 '
b00000000000000000000000100011100 (
b00000000000000000000000100100000 )
b00000000000000000000000100100000 *
#171
0#
#172
1#
b00000000000000000000000100100000 '
b00000000000000000000000100100000 (
b00000000000000000000000100100100 )
b00000000000000000000000100100100 *
#173
0#
#174
1#
b00000000000000000000000100100100 '
b00000000000000000000000100100100 (
b00000000000000000000000100101000 )
b00000000000000000000000100101000 *
#175
0#
#176
1#
b00000000000000000000000100101000 '
b00000000000000000000000100101000 (
b00000000000000000000000100101100 )
b00000000000000000000000100101100 *
#177
0#
#178
1#
b00000000000000000000000100101100 '
b00000000000000000000000100101100 (
b00000000000000000000000100110000 )
b00000000000000000000000100110000 *
#179
0#
#180
1#
b00000000000000000000000100110000 '
b00000000000000000000000100110000 (
b00000000000000000000000100110100 )
b00000000000000000000000100110100 *
#181
0#
#182
1#
b00000000000000000000000100110100 '
b00000000000000000000000100110100 (
b00000000000000000000000100111000 )
b00000000000000000000000100111000 *
#183
0#
#184
1#
b00000000000000000000000100111000 '
b00000000000000000000000100111000 (
b00000000000000000000000100111100 )
b00000000000000000000000100111100 *
#185
0#
#186
1#
b00000000000000000000000100111100 '
b00000000000000000000000100111100 (
b00000000000000000000000101000000 )
b00000000000000000000000101000000 *
#187
0#
#188
1#
b00000000000000000000000101000000 '
b00000000000000000000000101000000 (
b00000000000000000000000101000100 )
b00000000000000000000000101000100 *
#189
0#
#190
1#
b00000000000000000000000101000100 '
b00000000000000000000000101000100 (
b00000000000000000000000101001000 )
b00000000000000000000000101001000 *
#191
0#
#192
1#
b00000000000000000000000101001000 '
b00000000000000000000000101001000 (
b00000000000000000000000101001100 )
b00000000000000000000000101001100 *
#193
0#
#194
1#
b00000000000000000000000101001100 '
b00000000000000000000000101001100 (
b00000000000000000000000101010000 )
b00000000000000000000000101010000 *
#195
0#
#196
1#
b00000000000000000000000101010000 '
b00000000000000000000000101010000 (
b00000000000000000000000101010100 )
b00000000000000000000000101010100 *
#197
0#
#198
1#
b00000000000000000000000101010100 '
b00000000000000000000000101010100 (
b00000000000000000000000101011000 )
b00000000000000000000000101011000 *
